odoo/addons/shopfloor_reception_refund_return/README.rst
odoo/addons/shopfloor_reception_refund_return/__init__.py
odoo/addons/shopfloor_reception_refund_return/__manifest__.py
odoo/addons/shopfloor_reception_refund_return/actions/__init__.py
odoo/addons/shopfloor_reception_refund_return/actions/stock.py
odoo/addons/shopfloor_reception_refund_return/i18n/it.po
odoo/addons/shopfloor_reception_refund_return/i18n/shopfloor_reception_refund_return.pot
odoo/addons/shopfloor_reception_refund_return/readme/CONTRIBUTORS.rst
odoo/addons/shopfloor_reception_refund_return/readme/DESCRIPTION.rst
odoo/addons/shopfloor_reception_refund_return/static/description/icon.png
odoo/addons/shopfloor_reception_refund_return/static/description/index.html
odoo/addons/shopfloor_reception_refund_return/tests/__init__.py
odoo/addons/shopfloor_reception_refund_return/tests/test_action_stock.py
odoo_addon_shopfloor_reception_refund_return-16.0.1.0.0.3.dist-info/METADATA
odoo_addon_shopfloor_reception_refund_return-16.0.1.0.0.3.dist-info/WHEEL
odoo_addon_shopfloor_reception_refund_return-16.0.1.0.0.3.dist-info/top_level.txt
odoo_addon_shopfloor_reception_refund_return-16.0.1.0.0.3.dist-info/RECORD
