Metadata-Version: 2.1
Name: odoo-addon-shopfloor_reception_refund_return
Version: 16.0.1.0.0.3
Summary: Mark created return as to refund
Home-page: https://github.com/OCA/wms
Author: Camptocamp, BCIM, Odoo Community Association (OCA)
Author-email: support@odoo-community.org
License: AGPL-3
Classifier: Programming Language :: Python
Classifier: Framework :: Odoo
Classifier: Framework :: Odoo :: 16.0
Classifier: License :: OSI Approved :: GNU Affero General Public License v3
Requires-Python: >=3.10
Requires-Dist: odoo-addon-shopfloor<16.1dev,>=16.0dev
Requires-Dist: odoo<16.1dev,>=16.0a
